pubmedtools/__init__.py
pubmedtools/prepenv.py
pubmedtools/search.py
pubmedtools-0.0.0.2.dist-info/METADATA
pubmedtools-0.0.0.2.dist-info/WHEEL
pubmedtools-0.0.0.2.dist-info/top_level.txt
pubmedtools-0.0.0.2.dist-info/RECORD
