Metadata-Version: 2.1
Name: pubmedtools
Version: 0.0.0.2
Summary: Pubmed Tools (pubmedtools) package provides functions forsearching and retrieving articles from the PubMed databaseusing Biopython and NCBI Entrez Direct.
Home-page: https://github.com/diogomachado-bioinfo/pubmedtools
Author: Diogo de J. S. Machado
Author-email: diogomachado.bioinfo@gmail.com
License: BSD-3-Clause
Requires-Dist: pandas
Requires-Dist: biopython
